{
  "_class": "shapePath",
  "booleanOperation": -1,
  "do_objectID": "4920C852-DB3C-447F-BCDC-A9A00CE3B621",
  "edited": true,
  "exportOptions": {
    "_class": "exportOptions",
    "do_objectID": "4EEDB87A-FB69-427B-8528-9E40E0CBA23F",
    "exportFormats": [
    ],
    "includedLayerIds": [
    ],
    "layerOptions": 0,
    "shouldTrim": false
  },
  "frame": {
    "_class": "rect",
    "constrainProportions": false,
    "do_objectID": "D07279C8-CC99-4FC9-8018-54CEB8D99DC6",
    "height": 15,
    "width": 9,
    "x": 0,
    "y": 0
  },
  "isClosed": true,
  "isFlippedHorizontal": false,
  "isFlippedVertical": false,
  "isLocked": false,
  "isVisible": true,
  "layerListExpandedType": 0,
  "name": "Path",
  "nameIsFixed": false,
  "pointRadiusBehaviour": 1,
  "points": [
    {
      "_class": "curvePoint",
      "cornerRadius": 0,
      "curveFrom": "{0, 0.88400000000000034}",
      "curveMode": 1,
      "curveTo": "{0, 0.88400000000000034}",
      "hasCurveFrom": false,
      "hasCurveTo": false,
      "point": "{0, 0.88400000000000034}"
    },
    {
      "_class": "curvePoint",
      "cornerRadius": 0,
      "curveFrom": "{0.62135922330099946, 0.5}",
      "curveMode": 1,
      "curveTo": "{0.62135922330099946, 0.5}",
      "hasCurveFrom": false,
      "hasCurveTo": false,
      "point": "{0.62135922330099946, 0.5}"
    },
    {
      "_class": "curvePoint",
      "cornerRadius": 0,
      "curveFrom": "{0, 0.117999999999995}",
      "curveMode": 1,
      "curveTo": "{0, 0.117999999999995}",
      "hasCurveFrom": false,
      "hasCurveTo": false,
      "point": "{0, 0.117999999999995}"
    },
    {
      "_class": "curvePoint",
      "cornerRadius": 0,
      "curveFrom": "{0.1909385113268543, 0}",
      "curveMode": 1,
      "curveTo": "{0.1909385113268543, 0}",
      "hasCurveFrom": false,
      "hasCurveTo": false,
      "point": "{0.1909385113268543, 0}"
    },
    {
      "_class": "curvePoint",
      "cornerRadius": 0,
      "curveFrom": "{1, 0.5}",
      "curveMode": 1,
      "curveTo": "{1, 0.5}",
      "hasCurveFrom": false,
      "hasCurveTo": false,
      "point": "{1, 0.5}"
    },
    {
      "_class": "curvePoint",
      "cornerRadius": 0,
      "curveFrom": "{0.1909385113268543, 1}",
      "curveMode": 1,
      "curveTo": "{0.1909385113268543, 1}",
      "hasCurveFrom": false,
      "hasCurveTo": false,
      "point": "{0.1909385113268543, 1}"
    }
  ],
  "resizingConstraint": 63,
  "resizingType": 0,
  "rotation": 0,
  "shouldBreakMaskChain": false
}