{
  "_class": "group",
  "do_objectID": "45AF5509-3E87-4F99-AB89-16F539E5A6AD",
  "exportOptions": {
    "_class": "exportOptions",
    "do_objectID": "4CAB7E1B-8336-45A7-9C1C-340C7D66B039",
    "exportFormats": [
    ],
    "includedLayerIds": [
    ],
    "layerOptions": 0,
    "shouldTrim": false
  },
  "frame": {
    "_class": "rect",
    "constrainProportions": false,
    "do_objectID": "A82CBBE7-F2BB-4111-871C-3E430D0A42A9",
    "height": 190,
    "width": 650,
    "x": 530,
    "y": 2433
  },
  "hasClickThrough": false,
  "isFlippedHorizontal": false,
  "isFlippedVertical": false,
  "isLocked": false,
  "isVisible": true,
  "layerListExpandedType": 0,
  "layers": [
    {
      "class": "text",
      "id": "D2EEC358-D07D-4E4F-8DEA-446603DDCB0B"
    },
    {
      "class": "text",
      "id": "852B789B-3FAD-49E6-99A4-D0FF8551602C"
    },
    {
      "class": "text",
      "id": "A292E488-DC4A-4E56-8AC0-AE8CFBCD1D76"
    },
    {
      "class": "text",
      "id": "B1A3861E-10D9-4DD0-AFC3-DD137873B53A"
    },
    {
      "class": "text",
      "id": "80BA490E-616E-467A-9349-20B86C2FE73B"
    }
  ],
  "name": "Group 39",
  "nameIsFixed": false,
  "resizingConstraint": 63,
  "resizingType": 0,
  "rotation": 0,
  "shouldBreakMaskChain": false,
  "style": {
    "_class": "style",
    "do_objectID": "1C4D1E17-C4F5-48D7-9D8D-2A9E78ED74E7",
    "endDecorationType": 0,
    "miterLimit": 10,
    "startDecorationType": 0
  }
}