{
  "_class": "shapePath",
  "booleanOperation": -1,
  "do_objectID": "ADB325CC-537D-4613-BD84-59C9FBC2D57F",
  "edited": true,
  "exportOptions": {
    "_class": "exportOptions",
    "do_objectID": "D35D0782-84E0-48DA-9D86-44AF447C8DB7",
    "exportFormats": [
    ],
    "includedLayerIds": [
    ],
    "layerOptions": 0,
    "shouldTrim": false
  },
  "frame": {
    "_class": "rect",
    "constrainProportions": false,
    "do_objectID": "8B019E32-0C80-47FB-BBD3-838676A6DE51",
    "height": 20,
    "width": 12,
    "x": 0,
    "y": 0
  },
  "isClosed": true,
  "isFlippedHorizontal": false,
  "isFlippedVertical": false,
  "isLocked": false,
  "isVisible": true,
  "layerListExpandedType": 0,
  "name": "Path",
  "nameIsFixed": false,
  "pointRadiusBehaviour": 1,
  "points": [
    {
      "_class": "curvePoint",
      "cornerRadius": 0,
      "curveFrom": "{0, 0.88400000000000034}",
      "curveMode": 1,
      "curveTo": "{0, 0.88400000000000034}",
      "hasCurveFrom": false,
      "hasCurveTo": false,
      "point": "{0, 0.88400000000000034}"
    },
    {
      "_class": "curvePoint",
      "cornerRadius": 0,
      "curveFrom": "{0.62135922330099946, 0.5}",
      "curveMode": 1,
      "curveTo": "{0.62135922330099946, 0.5}",
      "hasCurveFrom": false,
      "hasCurveTo": false,
      "point": "{0.62135922330099946, 0.5}"
    },
    {
      "_class": "curvePoint",
      "cornerRadius": 0,
      "curveFrom": "{0, 0.117999999999995}",
      "curveMode": 1,
      "curveTo": "{0, 0.117999999999995}",
      "hasCurveFrom": false,
      "hasCurveTo": false,
      "point": "{0, 0.117999999999995}"
    },
    {
      "_class": "curvePoint",
      "cornerRadius": 0,
      "curveFrom": "{0.1909385113268543, 0}",
      "curveMode": 1,
      "curveTo": "{0.1909385113268543, 0}",
      "hasCurveFrom": false,
      "hasCurveTo": false,
      "point": "{0.1909385113268543, 0}"
    },
    {
      "_class": "curvePoint",
      "cornerRadius": 0,
      "curveFrom": "{1, 0.5}",
      "curveMode": 1,
      "curveTo": "{1, 0.5}",
      "hasCurveFrom": false,
      "hasCurveTo": false,
      "point": "{1, 0.5}"
    },
    {
      "_class": "curvePoint",
      "cornerRadius": 0,
      "curveFrom": "{0.1909385113268543, 1}",
      "curveMode": 1,
      "curveTo": "{0.1909385113268543, 1}",
      "hasCurveFrom": false,
      "hasCurveTo": false,
      "point": "{0.1909385113268543, 1}"
    }
  ],
  "resizingConstraint": 63,
  "resizingType": 0,
  "rotation": 0,
  "shouldBreakMaskChain": false
}