{
  "_class": "shapeGroup",
  "clippingMaskMode": 0,
  "do_objectID": "F9633707-2EED-431F-A8CF-F28042FE790F",
  "exportOptions": {
    "_class": "exportOptions",
    "do_objectID": "3EF3E873-A578-47F2-8984-0B6E73E8441A",
    "exportFormats": [
    ],
    "includedLayerIds": [
    ],
    "layerOptions": 0,
    "shouldTrim": false
  },
  "frame": {
    "_class": "rect",
    "constrainProportions": false,
    "do_objectID": "64BB7861-5F50-4885-AC13-2132E79A01DB",
    "height": 1,
    "width": 320,
    "x": 0,
    "y": 31
  },
  "hasClickThrough": false,
  "hasClippingMask": false,
  "isFlippedHorizontal": false,
  "isFlippedVertical": false,
  "isLocked": false,
  "isVisible": true,
  "layerListExpandedType": 1,
  "layers": [
    {
      "class": "rectangle",
      "id": "9F5A7806-1D66-455F-B5A2-213CBBA91FDD"
    }
  ],
  "name": "Rectangle 3 Copy",
  "nameIsFixed": false,
  "resizingConstraint": 63,
  "resizingType": 0,
  "rotation": 0,
  "shouldBreakMaskChain": false,
  "style": {
    "_class": "style",
    "borders": [
      {
        "_class": "border",
        "color": {
          "_class": "color",
          "alpha": 1,
          "blue": 0.592,
          "green": 0.592,
          "red": 0.592
        },
        "fillType": 0,
        "isEnabled": false,
        "position": 1,
        "thickness": 1
      }
    ],
    "do_objectID": "1A05BD96-C5F5-472F-B90D-3C4F001924E5",
    "endDecorationType": 0,
    "fills": [
      {
        "_class": "fill",
        "color": {
          "_class": "color",
          "alpha": 1,
          "blue": 0.9372549019607843,
          "green": 0.8901960784313725,
          "red": 0.9215686274509803
        },
        "fillType": 0,
        "isEnabled": true,
        "noiseIndex": 0,
        "noiseIntensity": 0,
        "patternFillType": 1,
        "patternTileScale": 1
      }
    ],
    "miterLimit": 10,
    "startDecorationType": 0
  },
  "windingRule": 1
}